h3ds/__init__.py
h3ds/affine_transform.py
h3ds/config_v1.toml
h3ds/config_v2.toml
h3ds/dataset.py
h3ds/log.py
h3ds/mesh.py
h3ds/numeric.py
h3ds/utils.py
h3ds-0.4.0.dist-info/LICENSE
h3ds-0.4.0.dist-info/METADATA
h3ds-0.4.0.dist-info/WHEEL
h3ds-0.4.0.dist-info/top_level.txt
h3ds-0.4.0.dist-info/RECORD
