Metadata-Version: 2.1
Name: h3ds
Version: 0.4.0
Summary: Python interface for H3DS dataset
Home-page: https://test.pypi.org/project/h3ds/
Author: Crisalix SA
Author-email: core.dl@crisalix.com
Project-URL: Bug Tracker, https://github.com/CrisalixSA/h3ds/issues
Project-URL: Project Website, https://crisalixsa.github.io/h3d-net/
Classifier: Programming Language :: Python :: 3
Classifier: License :: OSI Approved :: MIT License
Classifier: Operating System :: OS Independent
License-File: LICENSE
Requires-Dist: toml
Requires-Dist: requests
Requires-Dist: trimesh
Requires-Dist: Pillow
Requires-Dist: tqdm
Requires-Dist: opencv-python
Requires-Dist: scipy
Requires-Dist: matplotlib
Requires-Dist: gdown
